pyautograd/__init__.py
pyautograd-1.1.0.dist-info/METADATA
pyautograd-1.1.0.dist-info/WHEEL
pyautograd-1.1.0.dist-info/top_level.txt
pyautograd-1.1.0.dist-info/RECORD
