Metadata-Version: 2.1
Name: pyautograd
Version: 1.1.0
Summary: An auto-differentiation library for scalars
Home-page: https://github.com/affanhamid/autograd
Author: Affan Hamid
Author-email: affanhamid007@gmail.com
Classifier: Programming Language :: Python :: 3
Classifier: License :: OSI Approved :: MIT License
Classifier: Operating System :: OS Independent
Requires-Python: >=3.6
Requires-Dist: numpy
